dropboxdol/__init__.py
dropboxdol/base.py
dropboxdol/connection.py
dropboxdol/util.py
dropboxdol/tests/__init__.py
dropboxdol/tests/base_test.py
dropboxdol/tests/test_dropbox.py
dropboxdol-0.0.7.dist-info/LICENSE
dropboxdol-0.0.7.dist-info/METADATA
dropboxdol-0.0.7.dist-info/WHEEL
dropboxdol-0.0.7.dist-info/top_level.txt
dropboxdol-0.0.7.dist-info/RECORD
