Metadata-Version: 2.1
Name: dropboxdol
Version: 0.0.7
Summary: dropbox with a simple (dict-like or list-like) interface
Home-page: https://github.com/i2mint/dropboxdol
License: apache-2.0
Keywords: dropbox,data access
Platform: any
License-File: LICENSE
Requires-Dist: dol
Requires-Dist: dropbox
